{
  "typeName": "Cloudsoft::Terraform::Template",
  "description": "The Cloudsoft::Terraform::Template resource creates and manages a terraform template, through an existing terraform server",
  "sourceUrl": "https://github.com/cloudsoft/aws-cfn-connector-for-terraform",
  "properties": {
    "Name": {
      "description": "Terraform infrastructure name",
      "type": "string"
    },
    
    "ConfigurationContent": {
      "description": "Inlined terraform configuration, passed to the terraform server.",
      "type": "string"
    },
    "ConfigurationUrl": {
      "description": "Public HTTP URL of a terraform configuration. This will be downloaded and used by the terraform server.",
      "type": "string",
      "pattern": "^https?://.+$"
    },
    "ConfigurationS3Path": {
      "description": "S3 path object representing a terraform configuration. The current account must have access to this resource. This will be downloaded and used by the terraform server.",
      "type": "string",
      "pattern": "^s3://.+$"
    }
  },
  "readOnlyProperties": [
    "/properties/Name"
  ],
  "oneOf": [
    {
      "$ref": "#/properties/ConfigurationContent"
    },
    {
      "$ref": "#/properties/ConfigurationUrl"
    },
    {
      "$ref": "#/properties/ConfigurationS3Path"
    }
  ],
  "required": [],
  "primaryIdentifier": [
    "/properties/Name",
    "/properties/ConfigurationContent",
    "/properties/ConfigurationUrl",
    "/properties/ConfigurationS3Path"
  ],
  "handlers": {
    "create": {
      "permissions": [
        "initech:CreateInfrastructure"
      ]
    },
    "read": {
      "permissions": [
        "initech:DescribeInfrastructure"
      ]
    },
    "update": {
      "permissions": [
        "initech:UpdateInfrastructure"
      ]
    },
    "delete": {
      "permissions": [
        "initech:DeleteInfrastructure"
      ]
    },
    "list": {
      "permissions": [
        "initech:ListInfrastructures"
      ]
    }
  }
}
